hypixelio/__init__.py
hypixelio/base.py
hypixelio/endpoints.py
hypixelio/_async/__init__.py
hypixelio/_async/client.py
hypixelio/_async/converters.py
hypixelio/_async/portal.py
hypixelio/_async/utils.py
hypixelio/exceptions/__init__.py
hypixelio/exceptions/exceptions.py
hypixelio/lib/__init__.py
hypixelio/lib/client.py
hypixelio/lib/converters.py
hypixelio/lib/utils.py
hypixelio/models/__init__.py
hypixelio/models/boosters.py
hypixelio/models/find_guild.py
hypixelio/models/friends.py
hypixelio/models/games.py
hypixelio/models/guild.py
hypixelio/models/key.py
hypixelio/models/leaderboard.py
hypixelio/models/player.py
hypixelio/models/player_status.py
hypixelio/models/recent_games.py
hypixelio/models/watchdog.py
hypixelio/models/skyblock/__init__.py
hypixelio/models/skyblock/auction.py
hypixelio/models/skyblock/news.py
hypixelio/models/skyblock/active_auctions/__init__.py
hypixelio/models/skyblock/active_auctions/active_auctions.py
hypixelio/models/skyblock/bazaar/__init__.py
hypixelio/models/skyblock/bazaar/bazaar_item.py
hypixelio/models/skyblock/bazaar/skyblock_bazaar.py
hypixelio/models/skyblock/profile/__init__.py
hypixelio/models/skyblock/profile/profile.py
hypixelio/models/skyblock/profile/profile_member.py
hypixelio/models/skyblock/user_auction/__init__.py
hypixelio/models/skyblock/user_auction/user_auction.py
hypixelio/utils/__init__.py
hypixelio/utils/constants.py
hypixelio/utils/time.py
hypixelio/utils/url.py
HypixelIO-1.4.0.dist-info/LICENSE
HypixelIO-1.4.0.dist-info/METADATA
HypixelIO-1.4.0.dist-info/WHEEL
HypixelIO-1.4.0.dist-info/top_level.txt
HypixelIO-1.4.0.dist-info/RECORD
