Metadata-Version: 2.1
Name: HypixelIO
Version: 1.4.0
Summary: A modern, efficient and better way of interacting with the Hypixel API!
Home-page: https://github.com/janaSunrise/HypixelIO
Author: Sunrit Jana
Author-email: warriordefenderz@gmail.com
License: MIT
Project-URL: Documentation, https://github.com/janaSunrise/HypixelIO
Project-URL: Issue tracker, https://github.com/janaSunrise/HypixelIO/issues
Platform: UNKNOWN
Classifier: Programming Language :: Python :: 3
Classifier: Programming Language :: Python :: 3.7
Classifier: Programming Language :: Python :: 3.8
Classifier: Programming Language :: Python :: Implementation :: CPython
Classifier: License :: OSI Approved :: MIT License
Classifier: Operating System :: OS Independent
Classifier: Intended Audience :: Developers
Classifier: Natural Language :: English
Classifier: Typing :: Typed
Requires-Python: >=3.7
License-File: LICENSE
Requires-Dist: requests (==2.25.1)
Requires-Dist: aiohttp (==3.7.4.post0)
Provides-Extra: all
Requires-Dist: aiodns (>=1.1) ; extra == 'all'
Requires-Dist: Brotli (==1.0.9) ; extra == 'all'
Requires-Dist: cchardet (==2.1.7) ; extra == 'all'
Provides-Extra: speedups
Requires-Dist: aiodns (>=1.1) ; extra == 'speedups'
Requires-Dist: Brotli (==1.0.9) ; extra == 'speedups'
Requires-Dist: cchardet (==2.1.7) ; extra == 'speedups'
